[
    {
      "id": 1,
      "channel": "eBay",
      "order_date": "Aug 16, 2021",
      "order_id": "10912",
      "item": "Eyebogler Men's Regular Fit T-shirt",
      "qty": "10",
      "order_status": "Pending",
      "shipped_date": "-",
      "buyer": "Rohan Sahu",
      "shipped_country": "India",
      "action": ""
    },
    {
      "id": 2,
      "channel": "Amazon",
      "order_date": "Aug 16, 2021",
      "order_id": "10912",
      "item": "Eyebogler Men's Regular Fit T-shirt",
      "qty": "10",
      "order_status": "Pending",
      "shipped_date": "-",
      "buyer": "Rohan Sahu",
      "shipped_country": "India",
      "action": ""
    },
    {
      "id": 3,
      "channel": "eBay",
      "order_date": "Aug 16, 2021",
      "order_id": "10912",
      "item": "Eyebogler Men's Regular Fit T-shirt",
      "qty": "10",
      "order_status": "Pending",
      "shipped_date": "-",
      "buyer": "Rohan Sahu",
      "shipped_country": "India",
      "action": ""
    }
]